{"account_id":"Tiger_stats.json","account_display_name":"","account_emoji":"","account_description":"","account_name":"jian zhu chen","broker":"PU Prime Ltd","balance":10013.55,"equity":10013.55,"currency":"USC","updated_at":"2026-06-03T23:17:00+00:00","deposits":[{"date":"2026-05-30","amount":5008.00,"note":"","source":"ea"},{"date":"2026-05-30","amount":5000.00,"note":"","source":"ea"}],"stats":{"DAY":[{"label":"2026-06-03","trades":4,"total_lots":0.04,"profit":5.55,"win_trades":3,"loss_trades":1,"win_profit":7.88,"loss_profit":-2.33,"max_drawdown":-10.51,"max_float_profit":26.31,"balance_end":10013.55,"min_hold_sec":336,"avg_hold_sec":7679,"max_hold_sec":15240,"max_mae":-1552.0,"avg_mae":-921.7,"max_mfe":762.0,"avg_mfe":482.0,"orders":[{"ticket":203603499,"open_time":"2026-06-03T13:26:24+00:00","close_time":"2026-06-03T13:32:00+00:00","type":1,"lots":0.01,"open_price":4455.63000,"close_price":4460.77000,"profit":5.14,"hold_sec":336,"mae":-657.0,"mfe":203.0},{"ticket":203603508,"open_time":"2026-06-03T13:13:00+00:00","close_time":"2026-06-03T13:32:01+00:00","type":1,"lots":0.01,"open_price":4460.34000,"close_price":4460.68000,"profit":0.34,"hold_sec":1141,"mae":-399.0,"mfe":674.0},{"ticket":203973483,"open_time":"2026-06-03T19:23:40+00:00","close_time":"2026-06-03T23:17:00+00:00","type":1,"lots":0.01,"open_price":4436.65000,"close_price":4439.05000,"profit":2.40,"hold_sec":14000,"mae":-1552.0,"mfe":289.0},{"ticket":203973484,"open_time":"2026-06-03T19:03:00+00:00","close_time":"2026-06-03T23:17:00+00:00","type":1,"lots":0.01,"open_price":4441.38000,"close_price":4439.05000,"profit":-2.33,"hold_sec":15240,"mae":-1079.0,"mfe":762.0}]}],"WEEK":[{"label":"2026-W29","trades":4,"total_lots":0.04,"profit":5.55,"win_trades":3,"loss_trades":1,"win_profit":7.88,"loss_profit":-2.33,"max_drawdown":-10.51,"max_float_profit":26.31,"balance_end":10013.55,"min_hold_sec":336,"avg_hold_sec":7679,"max_hold_sec":15240,"max_mae":-1552.0,"avg_mae":-921.7,"max_mfe":762.0,"avg_mfe":482.0,"orders":[{"ticket":203603499,"open_time":"2026-06-03T13:26:24+00:00","close_time":"2026-06-03T13:32:00+00:00","type":1,"lots":0.01,"open_price":4455.63000,"close_price":4460.77000,"profit":5.14,"hold_sec":336,"mae":-657.0,"mfe":203.0},{"ticket":203603508,"open_time":"2026-06-03T13:13:00+00:00","close_time":"2026-06-03T13:32:01+00:00","type":1,"lots":0.01,"open_price":4460.34000,"close_price":4460.68000,"profit":0.34,"hold_sec":1141,"mae":-399.0,"mfe":674.0},{"ticket":203973483,"open_time":"2026-06-03T19:23:40+00:00","close_time":"2026-06-03T23:17:00+00:00","type":1,"lots":0.01,"open_price":4436.65000,"close_price":4439.05000,"profit":2.40,"hold_sec":14000,"mae":-1552.0,"mfe":289.0},{"ticket":203973484,"open_time":"2026-06-03T19:03:00+00:00","close_time":"2026-06-03T23:17:00+00:00","type":1,"lots":0.01,"open_price":4441.38000,"close_price":4439.05000,"profit":-2.33,"hold_sec":15240,"mae":-1079.0,"mfe":762.0}]}],"MONTH":[{"label":"2026-06","trades":4,"total_lots":0.04,"profit":5.55,"win_trades":3,"loss_trades":1,"win_profit":7.88,"loss_profit":-2.33,"max_drawdown":-10.51,"max_float_profit":26.31,"balance_end":10013.55,"min_hold_sec":336,"avg_hold_sec":7679,"max_hold_sec":15240,"max_mae":-1552.0,"avg_mae":-921.7,"max_mfe":762.0,"avg_mfe":482.0,"orders":[{"ticket":203603499,"open_time":"2026-06-03T13:26:24+00:00","close_time":"2026-06-03T13:32:00+00:00","type":1,"lots":0.01,"open_price":4455.63000,"close_price":4460.77000,"profit":5.14,"hold_sec":336,"mae":-657.0,"mfe":203.0},{"ticket":203603508,"open_time":"2026-06-03T13:13:00+00:00","close_time":"2026-06-03T13:32:01+00:00","type":1,"lots":0.01,"open_price":4460.34000,"close_price":4460.68000,"profit":0.34,"hold_sec":1141,"mae":-399.0,"mfe":674.0},{"ticket":203973483,"open_time":"2026-06-03T19:23:40+00:00","close_time":"2026-06-03T23:17:00+00:00","type":1,"lots":0.01,"open_price":4436.65000,"close_price":4439.05000,"profit":2.40,"hold_sec":14000,"mae":-1552.0,"mfe":289.0},{"ticket":203973484,"open_time":"2026-06-03T19:03:00+00:00","close_time":"2026-06-03T23:17:00+00:00","type":1,"lots":0.01,"open_price":4441.38000,"close_price":4439.05000,"profit":-2.33,"hold_sec":15240,"mae":-1079.0,"mfe":762.0}]}],"QUARTER":[{"label":"2026Q2","trades":4,"total_lots":0.04,"profit":5.55,"win_trades":3,"loss_trades":1,"win_profit":7.88,"loss_profit":-2.33,"max_drawdown":-10.51,"max_float_profit":26.31,"balance_end":10013.55,"min_hold_sec":336,"avg_hold_sec":7679,"max_hold_sec":15240,"max_mae":-1552.0,"avg_mae":-921.7,"max_mfe":762.0,"avg_mfe":482.0,"orders":[{"ticket":203603499,"open_time":"2026-06-03T13:26:24+00:00","close_time":"2026-06-03T13:32:00+00:00","type":1,"lots":0.01,"open_price":4455.63000,"close_price":4460.77000,"profit":5.14,"hold_sec":336,"mae":-657.0,"mfe":203.0},{"ticket":203603508,"open_time":"2026-06-03T13:13:00+00:00","close_time":"2026-06-03T13:32:01+00:00","type":1,"lots":0.01,"open_price":4460.34000,"close_price":4460.68000,"profit":0.34,"hold_sec":1141,"mae":-399.0,"mfe":674.0},{"ticket":203973483,"open_time":"2026-06-03T19:23:40+00:00","close_time":"2026-06-03T23:17:00+00:00","type":1,"lots":0.01,"open_price":4436.65000,"close_price":4439.05000,"profit":2.40,"hold_sec":14000,"mae":-1552.0,"mfe":289.0},{"ticket":203973484,"open_time":"2026-06-03T19:03:00+00:00","close_time":"2026-06-03T23:17:00+00:00","type":1,"lots":0.01,"open_price":4441.38000,"close_price":4439.05000,"profit":-2.33,"hold_sec":15240,"mae":-1079.0,"mfe":762.0}]}],"YEAR":[{"label":"2026","trades":4,"total_lots":0.04,"profit":5.55,"win_trades":3,"loss_trades":1,"win_profit":7.88,"loss_profit":-2.33,"max_drawdown":-10.51,"max_float_profit":26.31,"balance_end":10013.55,"min_hold_sec":336,"avg_hold_sec":7679,"max_hold_sec":15240,"max_mae":-1552.0,"avg_mae":-921.7,"max_mfe":762.0,"avg_mfe":482.0,"orders":[{"ticket":203603499,"open_time":"2026-06-03T13:26:24+00:00","close_time":"2026-06-03T13:32:00+00:00","type":1,"lots":0.01,"open_price":4455.63000,"close_price":4460.77000,"profit":5.14,"hold_sec":336,"mae":-657.0,"mfe":203.0},{"ticket":203603508,"open_time":"2026-06-03T13:13:00+00:00","close_time":"2026-06-03T13:32:01+00:00","type":1,"lots":0.01,"open_price":4460.34000,"close_price":4460.68000,"profit":0.34,"hold_sec":1141,"mae":-399.0,"mfe":674.0},{"ticket":203973483,"open_time":"2026-06-03T19:23:40+00:00","close_time":"2026-06-03T23:17:00+00:00","type":1,"lots":0.01,"open_price":4436.65000,"close_price":4439.05000,"profit":2.40,"hold_sec":14000,"mae":-1552.0,"mfe":289.0},{"ticket":203973484,"open_time":"2026-06-03T19:03:00+00:00","close_time":"2026-06-03T23:17:00+00:00","type":1,"lots":0.01,"open_price":4441.38000,"close_price":4439.05000,"profit":-2.33,"hold_sec":15240,"mae":-1079.0,"mfe":762.0}]}]}}